birder/__init__.py
birder/py.typed
birder/version.py
birder/adversarial/__init__.py
birder/adversarial/base.py
birder/adversarial/deepfool.py
birder/adversarial/fgsm.py
birder/adversarial/pgd.py
birder/adversarial/simba.py
birder/common/__init__.py
birder/common/cli.py
birder/common/fs_ops.py
birder/common/lib.py
birder/common/masking.py
birder/common/training_cli.py
birder/common/training_utils.py
birder/conf/__init__.py
birder/conf/settings.py
birder/data/__init__.py
birder/data/collators/__init__.py
birder/data/collators/detection.py
birder/data/dataloader/__init__.py
birder/data/dataloader/webdataset.py
birder/data/datasets/__init__.py
birder/data/datasets/coco.py
birder/data/datasets/directory.py
birder/data/datasets/fake.py
birder/data/datasets/webdataset.py
birder/data/transforms/__init__.py
birder/data/transforms/classification.py
birder/data/transforms/detection.py
birder/data/transforms/mosaic.py
birder/datahub/__init__.py
birder/datahub/_lib.py
birder/datahub/classification.py
birder/inference/__init__.py
birder/inference/classification.py
birder/inference/data_parallel.py
birder/inference/detection.py
birder/inference/wbf.py
birder/introspection/__init__.py
birder/introspection/attention_rollout.py
birder/introspection/base.py
birder/introspection/feature_pca.py
birder/introspection/gradcam.py
birder/introspection/guided_backprop.py
birder/introspection/transformer_attribution.py
birder/kernels/__init__.py
birder/kernels/load_kernel.py
birder/kernels/deformable_detr/ms_deform_attn.h
birder/kernels/deformable_detr/vision.cpp
birder/kernels/deformable_detr/cpu/ms_deform_attn_cpu.cpp
birder/kernels/deformable_detr/cpu/ms_deform_attn_cpu.h
birder/kernels/deformable_detr/cuda/ms_deform_attn_cuda.cu
birder/kernels/deformable_detr/cuda/ms_deform_attn_cuda.h
birder/kernels/deformable_detr/cuda/ms_deform_im2col_cuda.cuh
birder/kernels/soft_nms/op.cpp
birder/kernels/soft_nms/soft_nms.cpp
birder/kernels/soft_nms/soft_nms.h
birder/kernels/transnext/av_bw_kernel.cu
birder-0.4.2.dist-info/licenses/LICENSE
birder-0.4.2.dist-info/METADATA
birder-0.4.2.dist-info/WHEEL
birder-0.4.2.dist-info/entry_points.txt
birder-0.4.2.dist-info/top_level.txt
birder-0.4.2.dist-info/RECORD
