Metadata-Version: 2.4
Name: birder
Version: 0.4.2
Summary: An open-source computer vision framework for wildlife image analysis, featuring state-of-the-art models for species classification and detection.
Author: Ofer Hasson
License-Expression: Apache-2.0
Project-URL: Homepage, https://gitlab.com/birder/birder
Project-URL: Documentation, https://birder.gitlab.io/birder/
Project-URL: Issues, https://gitlab.com/birder/birder/-/issues
Keywords: computer-vision,image-classification,object-detection,pytorch,deep-learning
Classifier: Development Status :: 3 - Alpha
Classifier: Intended Audience :: Science/Research
Classifier: Intended Audience :: Developers
Classifier: Intended Audience :: Education
Classifier: Operating System :: OS Independent
Classifier: Programming Language :: Python :: 3
Classifier: Topic :: Scientific/Engineering
Classifier: Topic :: Scientific/Engineering :: Artificial Intelligence
Classifier: Topic :: Scientific/Engineering :: Image Recognition
Classifier: Topic :: Software Development
Classifier: Topic :: Software Development :: Libraries
Classifier: Topic :: Software Development :: Libraries :: Python Modules
Requires-Python: >=3.11
License-File: LICENSE
Requires-Dist: matplotlib>=3.9.0
Requires-Dist: numpy>=2.2.0
Requires-Dist: onnx>=1.18.0
Requires-Dist: onnxscript~=0.6.0
Requires-Dist: Pillow>=12.0.0
Requires-Dist: polars>=1.31.0
Requires-Dist: pyarrow>=20.0.0
Requires-Dist: pycocotools~=2.0.11
Requires-Dist: rich>=14.0.0
Requires-Dist: scikit-learn>=1.6.0
Requires-Dist: scipy>=1.15.0
Requires-Dist: tensorboard>=2.19.0
Requires-Dist: torchinfo~=1.8.0
Requires-Dist: torchmetrics~=1.8.2
Requires-Dist: tqdm>=4.67.0
Requires-Dist: webdataset>=0.2.111
Requires-Dist: torch>=2.7.0
Requires-Dist: torchvision
Provides-Extra: dev
Requires-Dist: altair~=5.5.0; extra == "dev"
Requires-Dist: bandit~=1.9.3; extra == "dev"
Requires-Dist: black~=26.1.0; extra == "dev"
Requires-Dist: build~=1.4.0; extra == "dev"
Requires-Dist: bumpver~=2025.1131; extra == "dev"
Requires-Dist: captum~=0.7.0; extra == "dev"
Requires-Dist: coverage~=7.13.2; extra == "dev"
Requires-Dist: debugpy; extra == "dev"
Requires-Dist: flake8-pep585~=0.1.7; extra == "dev"
Requires-Dist: flake8~=7.3.0; extra == "dev"
Requires-Dist: invoke~=2.2.1; extra == "dev"
Requires-Dist: ipython; extra == "dev"
Requires-Dist: isort~=7.0.0; extra == "dev"
Requires-Dist: Jinja2~=3.1.5; extra == "dev"
Requires-Dist: mkdocs~=1.6.1; extra == "dev"
Requires-Dist: mkdocs-exclude~=1.0.2; extra == "dev"
Requires-Dist: MonkeyType~=23.3.0; extra == "dev"
Requires-Dist: mypy~=1.19.1; extra == "dev"
Requires-Dist: parameterized~=0.9.0; extra == "dev"
Requires-Dist: pylint~=4.0.4; extra == "dev"
Requires-Dist: pytest; extra == "dev"
Requires-Dist: requests~=2.32.5; extra == "dev"
Requires-Dist: safetensors~=0.7.0; extra == "dev"
Requires-Dist: setuptools; extra == "dev"
Requires-Dist: torchao~=0.15.0; extra == "dev"
Requires-Dist: torchprofile==0.0.4; extra == "dev"
Requires-Dist: twine~=6.2.0; extra == "dev"
Requires-Dist: types-requests~=2.32.4; extra == "dev"
Requires-Dist: unidecode; extra == "dev"
Requires-Dist: urllib3~=2.6.2; extra == "dev"
Requires-Dist: wheel; extra == "dev"
Provides-Extra: hf
Requires-Dist: huggingface_hub; extra == "hf"
Requires-Dist: transformers; extra == "hf"
Dynamic: license-file
